examples/__init__.py
examples/example_01.py
examples/winequalityN.csv
sdfs/__init__.py
sdfs/concatenate_feature_sets.py
sdfs/distances.py
sdfs/dynamic_features.py
sdfs/early_stopping.py
sdfs/extend_test_samples.py
sdfs/feature_expansion.py
sdfs/models.py
sdfs/train.py
sdfs-1.0.3.dist-info/LICENSE.txt
sdfs-1.0.3.dist-info/METADATA
sdfs-1.0.3.dist-info/WHEEL
sdfs-1.0.3.dist-info/top_level.txt
sdfs-1.0.3.dist-info/RECORD
