Metadata-Version: 2.1
Name: sdfs
Version: 1.0.3
Summary: A novel preprocessing technique called Feature Expansion, designed to identify potentially overlooked input features using the Semi-Dynamic Feature Sets (SDFS) model.
Home-page: https://github.com/elahe-hosseini98/Semi-Dynamic-Feature-Set
Author: Elaheh Hosseini
Author-email: elahe.s.hs98@gmail.com
Classifier: Programming Language :: Python :: 3.9
Classifier: License :: OSI Approved :: MIT License
Classifier: Operating System :: OS Independent
Requires-Python: >=3.9
License-File: LICENSE.txt
Requires-Dist: torch >=1.9.0
Requires-Dist: numpy >=1.21.0
Requires-Dist: scipy >=1.7.0
Requires-Dist: scikit-learn >=0.24.0
Requires-Dist: pandas
